{
  "_class": "shapeGroup",
  "booleanOperation": 0,
  "clippingMaskMode": 0,
  "do_objectID": "4E7B12CE-AFCC-43C5-85D3-541FC2EE30AB",
  "exportOptions": {
    "_class": "exportOptions",
    "do_objectID": "9B72985D-065B-4DCA-9F7B-E333F01282F8",
    "exportFormats": [
    ],
    "includedLayerIds": [
    ],
    "layerOptions": 0,
    "shouldTrim": false
  },
  "frame": {
    "_class": "rect",
    "constrainProportions": false,
    "do_objectID": "06F001E4-F251-4A4A-8F3B-CA7B6368FFC5",
    "height": 55.99999999999999,
    "width": 100,
    "x": 0,
    "y": 0
  },
  "hasClickThrough": false,
  "hasClippingMask": true,
  "isFixedToViewport": false,
  "isFlippedHorizontal": false,
  "isFlippedVertical": false,
  "isLocked": false,
  "isVisible": true,
  "layerListExpandedType": 1,
  "layers": [
    {
      "class": "rectangle",
      "id": "E2FEA554-B89B-42FD-9EE4-CD9BCF73C0D0"
    },
    {
      "class": "rectangle",
      "id": "D8E991D1-E24D-4F52-8133-7CA1FA844118"
    },
    {
      "class": "rectangle",
      "id": "70FB0411-5FBA-4494-83A5-BCE6F47FAD7F"
    },
    {
      "class": "rectangle",
      "id": "D9DDB710-9B76-4A41-ADEC-C9AF0B9A4C4A"
    },
    {
      "class": "rectangle",
      "id": "8C242C2C-744A-4BAA-AC5C-B487726F6B34"
    }
  ],
  "name": "Surface",
  "nameIsFixed": true,
  "resizingConstraint": 63,
  "resizingType": 0,
  "rotation": 0,
  "sharedStyleID": "53A2FB4C-5462-404A-983B-BD0921D56DB0",
  "shouldBreakMaskChain": false,
  "style": {
    "_class": "style",
    "do_objectID": "9B8E7B82-5B40-4011-8401-BEA9BFAAE5B5",
    "endMarkerType": 0,
    "fills": [
      {
        "_class": "fill",
        "color": {
          "_class": "color",
          "alpha": 1,
          "blue": 0.5903220663265306,
          "green": 0.5903220663265306,
          "red": 0.5903220663265306
        },
        "fillType": 4,
        "image": {
          "_class": "MSJSONFileReference",
          "_ref": "images/172a30886ee983ac81cb2e7910a1f49d783c5e78.png",
          "_ref_class": "MSImageData"
        },
        "isEnabled": true,
        "noiseIndex": 0,
        "noiseIntensity": 0,
        "patternFillType": 1,
        "patternTileScale": 1
      }
    ],
    "miterLimit": 10,
    "startMarkerType": 0,
    "windingRule": 1
  },
  "userInfo": {
    "com.invisionlabs.duplicate": {
      "photos-duplicate": {
        "asTile": 0,
        "items": [
          {
            "link": "https://sv2.bitel.com.pe/sites/default/files/2018-09/giga%2B-call-600x433.jpg",
            "type": "src"
          },
          {
            "link": "https://sv2.bitel.com.pe/sites/default/files/2018-09/Cambiate-a-Bitel-600x433.jpg",
            "type": "src"
          },
          {
            "link": "https://sv2.bitel.com.pe/sites/default/files/2018-09/home-paquetes-1200x433.jpg",
            "type": "src"
          }
        ],
        "mode": "web"
      }
    }
  },
  "windingRule": 1
}