{
  "_class": "shapeGroup",
  "booleanOperation": 0,
  "clippingMaskMode": 0,
  "do_objectID": "8C16BD61-399E-455E-A390-897CB5ABE328",
  "exportOptions": {
    "_class": "exportOptions",
    "do_objectID": "B069D991-EB07-40DE-81B8-A2430B1BFEF6",
    "exportFormats": [
    ],
    "includedLayerIds": [
    ],
    "layerOptions": 0,
    "shouldTrim": false
  },
  "frame": {
    "_class": "rect",
    "constrainProportions": false,
    "do_objectID": "EEA869EF-FBC9-485D-BBA9-8C185F75F4E8",
    "height": 55.99999999999999,
    "width": 100,
    "x": 0,
    "y": 0
  },
  "hasClickThrough": false,
  "hasClippingMask": true,
  "isFixedToViewport": false,
  "isFlippedHorizontal": false,
  "isFlippedVertical": false,
  "isLocked": false,
  "isVisible": true,
  "layerListExpandedType": 1,
  "layers": [
    {
      "class": "rectangle",
      "id": "12499DAD-A0DF-4F51-B1A6-F7E4AD5D2521"
    },
    {
      "class": "rectangle",
      "id": "FE9F2636-DF1F-42C9-839B-82005AF2DF1C"
    },
    {
      "class": "rectangle",
      "id": "11D00A5A-202A-4B3A-8ECC-BE84BB5AB718"
    },
    {
      "class": "rectangle",
      "id": "568A4DF4-DB8A-41CA-9423-05F69AD800DB"
    },
    {
      "class": "rectangle",
      "id": "BDB6DFDD-96D7-4CEC-909D-D8722DA9306F"
    }
  ],
  "name": "Surface",
  "nameIsFixed": true,
  "resizingConstraint": 63,
  "resizingType": 0,
  "rotation": 0,
  "sharedStyleID": "53A2FB4C-5462-404A-983B-BD0921D56DB0",
  "shouldBreakMaskChain": false,
  "style": {
    "_class": "style",
    "do_objectID": "CCF2C97D-5D97-4355-AA54-24BBB376E562",
    "endMarkerType": 0,
    "fills": [
      {
        "_class": "fill",
        "color": {
          "_class": "color",
          "alpha": 1,
          "blue": 0.5903220663265306,
          "green": 0.5903220663265306,
          "red": 0.5903220663265306
        },
        "fillType": 4,
        "image": {
          "_class": "MSJSONFileReference",
          "_ref": "images/33a486bea75dc251355d5950a410caafaa610f2e.png",
          "_ref_class": "MSImageData"
        },
        "isEnabled": true,
        "noiseIndex": 0,
        "noiseIntensity": 0,
        "patternFillType": 1,
        "patternTileScale": 1
      }
    ],
    "miterLimit": 10,
    "startMarkerType": 0,
    "windingRule": 1
  },
  "userInfo": {
    "com.invisionlabs.duplicate": {
      "photos-duplicate": {
        "asTile": 0,
        "items": [
          {
            "link": "https://sv2.bitel.com.pe/sites/default/files/2018-09/giga%2B-call-600x433.jpg",
            "type": "src"
          },
          {
            "link": "https://sv2.bitel.com.pe/sites/default/files/2018-09/Cambiate-a-Bitel-600x433.jpg",
            "type": "src"
          },
          {
            "link": "https://sv2.bitel.com.pe/sites/default/files/2018-09/home-paquetes-1200x433.jpg",
            "type": "src"
          }
        ],
        "mode": "web"
      }
    }
  },
  "windingRule": 1
}