{
  "_class": "rectangle",
  "booleanOperation": 1,
  "clippingMaskMode": 0,
  "do_objectID": "A170B0AC-D19A-4A2A-9CEB-BEF14D73CE8B",
  "edited": false,
  "exportOptions": {
    "_class": "exportOptions",
    "do_objectID": "98412738-B3DC-4885-A32C-2617E39A3FD9",
    "exportFormats": [
    ],
    "includedLayerIds": [
    ],
    "layerOptions": 0,
    "shouldTrim": false
  },
  "fixedRadius": 0,
  "frame": {
    "_class": "rect",
    "constrainProportions": false,
    "do_objectID": "CBF6AE9F-219A-4C6D-B07C-BC65E4B507D1",
    "height": 16,
    "width": 16,
    "x": -8.000000000000028,
    "y": 47.99999999999996
  },
  "hasClippingMask": false,
  "hasConvertedToNewRoundCorners": true,
  "isClosed": true,
  "isFixedToViewport": false,
  "isFlippedHorizontal": false,
  "isFlippedVertical": false,
  "isLocked": false,
  "isVisible": false,
  "layerListExpandedType": 0,
  "name": "Cut 4",
  "nameIsFixed": false,
  "pointRadiusBehaviour": 1,
  "points": [
    {
      "_class": "curvePoint",
      "cornerRadius": 0,
      "curveFrom": "{0, 7.1054273576010019e-15}",
      "curveMode": 1,
      "curveTo": "{0, 7.1054273576010019e-15}",
      "hasCurveFrom": false,
      "hasCurveTo": false,
      "point": "{0, 7.1054273576010019e-15}"
    },
    {
      "_class": "curvePoint",
      "cornerRadius": 0,
      "curveFrom": "{1, 7.1054273576010019e-15}",
      "curveMode": 1,
      "curveTo": "{1, 7.1054273576010019e-15}",
      "hasCurveFrom": false,
      "hasCurveTo": false,
      "point": "{1, 7.1054273576010019e-15}"
    },
    {
      "_class": "curvePoint",
      "cornerRadius": 0,
      "curveFrom": "{1, 1.0000000000000071}",
      "curveMode": 1,
      "curveTo": "{1, 1.0000000000000071}",
      "hasCurveFrom": false,
      "hasCurveTo": false,
      "point": "{1, 1.0000000000000071}"
    },
    {
      "_class": "curvePoint",
      "cornerRadius": 0,
      "curveFrom": "{0, 1.0000000000000071}",
      "curveMode": 1,
      "curveTo": "{0, 1.0000000000000071}",
      "hasCurveFrom": false,
      "hasCurveTo": false,
      "point": "{0, 1.0000000000000071}"
    }
  ],
  "resizingConstraint": 33,
  "resizingType": 0,
  "rotation": -45,
  "shouldBreakMaskChain": false,
  "style": {
    "_class": "style",
    "do_objectID": "74FBF5C2-795C-471A-B1FC-B4ACE0CF672D",
    "endMarkerType": 0,
    "fills": [
      {
        "_class": "fill",
        "color": {
          "_class": "color",
          "alpha": 1,
          "blue": 0.5903220663265306,
          "green": 0.5903220663265306,
          "red": 0.5903220663265306
        },
        "fillType": 4,
        "image": {
          "_class": "MSJSONFileReference",
          "_ref": "images/91e998759ff091cf48390af445a532b4a4782d72.png",
          "_ref_class": "MSImageData"
        },
        "isEnabled": true,
        "noiseIndex": 0,
        "noiseIntensity": 0,
        "patternFillType": 1,
        "patternTileScale": 1
      }
    ],
    "miterLimit": 10,
    "startMarkerType": 0,
    "windingRule": 1
  }
}